<?xml version="1.0" encoding="utf-8"?>
<class id="1f4cee55-0197-49aa-941a-7d4dba029225" type="Minimum Dependency Versions" typeId="63605213-ab56-4042-b801-907bb5a79c08">
  <name>Minimum Dependency Versions</name>
  <display>Minimum Dependency Versions</display>
  <isAbstract>false</isAbstract>
  <sort-children>by-type-then-by-name</sort-children>
  <order>1</order>
  <genericTypes />
  <isMapped>false</isMapped>
  <parentFolderId>5d11bab6-4ad1-4ddb-b37f-64c439260fcc</parentFolderId>
  <packageId>5d11bab6-4ad1-4ddb-b37f-64c439260fcc</packageId>
  <packageName>Intent.ApplicationTemplate.Aws.Lambda.Functions</packageName>
  <stereotypes />
  <metadata />
  <childElements>
    <childElement id="e3ff0866-d6d1-42ba-8fd5-27a3b9e9aaf4" type="Module" typeId="6a811790-b322-4340-8b68-84dae5ffafa8">
      <name>Intent.AI.AutoImplementation</name>
      <display>Intent.AI.AutoImplementation 1.0.0-beta.19</display>
      <isAbstract>false</isAbstract>
      <value>1.0.0-beta.19</value>
      <genericTypes />
      <isMapped>false</isMapped>
      <parentFolderId>1f4cee55-0197-49aa-941a-7d4dba029225</parentFolderId>
      <packageId>5d11bab6-4ad1-4ddb-b37f-64c439260fcc</packageId>
      <packageName>Intent.ApplicationTemplate.Aws.Lambda.Functions</packageName>
      <stereotypes />
      <metadata />
      <childElements />
    </childElement>
    <childElement id="91f3b5ef-e792-4abb-82fc-ccbaa8221952" type="Module" typeId="6a811790-b322-4340-8b68-84dae5ffafa8">
      <name>Intent.AI.Blazor</name>
      <display>Intent.AI.Blazor 1.0.0-beta.21</display>
      <isAbstract>false</isAbstract>
      <value>1.0.0-beta.21</value>
      <genericTypes />
      <isMapped>false</isMapped>
      <parentFolderId>1f4cee55-0197-49aa-941a-7d4dba029225</parentFolderId>
      <packageId>5d11bab6-4ad1-4ddb-b37f-64c439260fcc</packageId>
      <packageName>Intent.ApplicationTemplate.Aws.Lambda.Functions</packageName>
      <stereotypes />
      <metadata />
      <childElements />
    </childElement>
    <childElement id="a1876cf6-c4c6-48df-8c86-c62616f11de9" type="Module" typeId="6a811790-b322-4340-8b68-84dae5ffafa8">
      <name>Intent.AI.UnitTests</name>
      <display>Intent.AI.UnitTests 1.0.0-beta.19</display>
      <isAbstract>false</isAbstract>
      <value>1.0.0-beta.19</value>
      <genericTypes />
      <isMapped>false</isMapped>
      <parentFolderId>1f4cee55-0197-49aa-941a-7d4dba029225</parentFolderId>
      <packageId>5d11bab6-4ad1-4ddb-b37f-64c439260fcc</packageId>
      <packageName>Intent.ApplicationTemplate.Aws.Lambda.Functions</packageName>
      <stereotypes />
      <metadata />
      <childElements />
    </childElement>
    <childElement id="7729a8a2-9f05-4487-959f-dd5c9ed6bdb2" type="Module" typeId="6a811790-b322-4340-8b68-84dae5ffafa8">
      <name>Intent.Application.AutoMapper</name>
      <display>Intent.Application.AutoMapper 5.3.4</display>
      <isAbstract>false</isAbstract>
      <value>5.3.4</value>
      <genericTypes />
      <isMapped>false</isMapped>
      <parentFolderId>1f4cee55-0197-49aa-941a-7d4dba029225</parentFolderId>
      <packageId>5d11bab6-4ad1-4ddb-b37f-64c439260fcc</packageId>
      <packageName>Intent.ApplicationTemplate.Aws.Lambda.Functions</packageName>
      <stereotypes />
      <metadata />
      <childElements />
    </childElement>
    <childElement id="9b663960-347b-4d90-8eae-59fc953ce335" type="Module" typeId="6a811790-b322-4340-8b68-84dae5ffafa8">
      <name>Intent.Application.Contracts</name>
      <display>Intent.Application.Contracts 5.1.2</display>
      <isAbstract>false</isAbstract>
      <value>5.1.2</value>
      <genericTypes />
      <isMapped>false</isMapped>
      <parentFolderId>1f4cee55-0197-49aa-941a-7d4dba029225</parentFolderId>
      <packageId>5d11bab6-4ad1-4ddb-b37f-64c439260fcc</packageId>
      <packageName>Intent.ApplicationTemplate.Aws.Lambda.Functions</packageName>
      <stereotypes />
      <metadata />
      <childElements />
    </childElement>
    <childElement id="e4a9d67d-7d2c-469f-bfdf-07280f1f0840" type="Module" typeId="6a811790-b322-4340-8b68-84dae5ffafa8">
      <name>Intent.Application.Contracts.Clients</name>
      <display>Intent.Application.Contracts.Clients 5.1.6</display>
      <isAbstract>false</isAbstract>
      <value>5.1.6</value>
      <genericTypes />
      <isMapped>false</isMapped>
      <parentFolderId>1f4cee55-0197-49aa-941a-7d4dba029225</parentFolderId>
      <packageId>5d11bab6-4ad1-4ddb-b37f-64c439260fcc</packageId>
      <packageName>Intent.ApplicationTemplate.Aws.Lambda.Functions</packageName>
      <stereotypes />
      <metadata />
      <childElements />
    </childElement>
    <childElement id="83cf8396-a5ae-430a-998b-fcdfac9cbdf5" type="Module" typeId="6a811790-b322-4340-8b68-84dae5ffafa8">
      <name>Intent.Application.DependencyInjection</name>
      <display>Intent.Application.DependencyInjection 4.1.13</display>
      <isAbstract>false</isAbstract>
      <value>4.1.13</value>
      <genericTypes />
      <isMapped>false</isMapped>
      <parentFolderId>1f4cee55-0197-49aa-941a-7d4dba029225</parentFolderId>
      <packageId>5d11bab6-4ad1-4ddb-b37f-64c439260fcc</packageId>
      <packageName>Intent.ApplicationTemplate.Aws.Lambda.Functions</packageName>
      <stereotypes />
      <metadata />
      <childElements />
    </childElement>
    <childElement id="e629fdea-749f-4094-924f-22081d14729f" type="Module" typeId="6a811790-b322-4340-8b68-84dae5ffafa8">
      <name>Intent.Application.DependencyInjection.MediatR</name>
      <display>Intent.Application.DependencyInjection.MediatR 3.6.2</display>
      <isAbstract>false</isAbstract>
      <value>3.6.2</value>
      <genericTypes />
      <isMapped>false</isMapped>
      <parentFolderId>1f4cee55-0197-49aa-941a-7d4dba029225</parentFolderId>
      <packageId>5d11bab6-4ad1-4ddb-b37f-64c439260fcc</packageId>
      <packageName>Intent.ApplicationTemplate.Aws.Lambda.Functions</packageName>
      <stereotypes />
      <metadata />
      <childElements />
    </childElement>
    <childElement id="5d2ee2d4-a936-4326-a88b-8e1a047bb26b" type="Module" typeId="6a811790-b322-4340-8b68-84dae5ffafa8">
      <name>Intent.Application.DomainInteractions</name>
      <display>Intent.Application.DomainInteractions 1.1.9</display>
      <isAbstract>false</isAbstract>
      <value>1.1.9</value>
      <genericTypes />
      <isMapped>false</isMapped>
      <parentFolderId>1f4cee55-0197-49aa-941a-7d4dba029225</parentFolderId>
      <packageId>5d11bab6-4ad1-4ddb-b37f-64c439260fcc</packageId>
      <packageName>Intent.ApplicationTemplate.Aws.Lambda.Functions</packageName>
      <stereotypes />
      <metadata />
      <childElements />
    </childElement>
    <childElement id="fe1b6d55-1ffa-4fb5-a567-e021d368d252" type="Module" typeId="6a811790-b322-4340-8b68-84dae5ffafa8">
      <name>Intent.Application.Dtos</name>
      <display>Intent.Application.Dtos 4.4.7</display>
      <isAbstract>false</isAbstract>
      <value>4.4.7</value>
      <genericTypes />
      <isMapped>false</isMapped>
      <parentFolderId>1f4cee55-0197-49aa-941a-7d4dba029225</parentFolderId>
      <packageId>5d11bab6-4ad1-4ddb-b37f-64c439260fcc</packageId>
      <packageName>Intent.ApplicationTemplate.Aws.Lambda.Functions</packageName>
      <stereotypes />
      <metadata />
      <childElements />
    </childElement>
    <childElement id="c44294cd-6125-40d4-98df-86138879227b" type="Module" typeId="6a811790-b322-4340-8b68-84dae5ffafa8">
      <name>Intent.Application.Dtos.AutoMapper</name>
      <display>Intent.Application.Dtos.AutoMapper 4.0.19</display>
      <isAbstract>false</isAbstract>
      <value>4.0.19</value>
      <genericTypes />
      <isMapped>false</isMapped>
      <parentFolderId>1f4cee55-0197-49aa-941a-7d4dba029225</parentFolderId>
      <packageId>5d11bab6-4ad1-4ddb-b37f-64c439260fcc</packageId>
      <packageName>Intent.ApplicationTemplate.Aws.Lambda.Functions</packageName>
      <stereotypes />
      <metadata />
      <childElements />
    </childElement>
    <childElement id="1ed1e3a0-daa4-4410-bc73-c2b1fb9b187e" type="Module" typeId="6a811790-b322-4340-8b68-84dae5ffafa8">
      <name>Intent.Application.Dtos.Pagination</name>
      <display>Intent.Application.Dtos.Pagination 4.1.4</display>
      <isAbstract>false</isAbstract>
      <value>4.1.4</value>
      <genericTypes />
      <isMapped>false</isMapped>
      <parentFolderId>1f4cee55-0197-49aa-941a-7d4dba029225</parentFolderId>
      <packageId>5d11bab6-4ad1-4ddb-b37f-64c439260fcc</packageId>
      <packageName>Intent.ApplicationTemplate.Aws.Lambda.Functions</packageName>
      <stereotypes />
      <metadata />
      <childElements />
    </childElement>
    <childElement id="6515601c-f513-4162-a460-4a3699fa223a" type="Module" typeId="6a811790-b322-4340-8b68-84dae5ffafa8">
      <name>Intent.Application.FluentValidation</name>
      <display>Intent.Application.FluentValidation 3.11.5</display>
      <isAbstract>false</isAbstract>
      <value>3.11.5</value>
      <genericTypes />
      <isMapped>false</isMapped>
      <parentFolderId>1f4cee55-0197-49aa-941a-7d4dba029225</parentFolderId>
      <packageId>5d11bab6-4ad1-4ddb-b37f-64c439260fcc</packageId>
      <packageName>Intent.ApplicationTemplate.Aws.Lambda.Functions</packageName>
      <stereotypes />
      <metadata />
      <childElements />
    </childElement>
    <childElement id="f2acf146-7472-4a2f-9ac5-05a522c258f5" type="Module" typeId="6a811790-b322-4340-8b68-84dae5ffafa8">
      <name>Intent.Application.FluentValidation.Dtos</name>
      <display>Intent.Application.FluentValidation.Dtos 3.12.4</display>
      <isAbstract>false</isAbstract>
      <value>3.12.4</value>
      <genericTypes />
      <isMapped>false</isMapped>
      <parentFolderId>1f4cee55-0197-49aa-941a-7d4dba029225</parentFolderId>
      <packageId>5d11bab6-4ad1-4ddb-b37f-64c439260fcc</packageId>
      <packageName>Intent.ApplicationTemplate.Aws.Lambda.Functions</packageName>
      <stereotypes />
      <metadata />
      <childElements />
    </childElement>
    <childElement id="2965db35-12ef-4720-944d-d32fc4af173d" type="Module" typeId="6a811790-b322-4340-8b68-84dae5ffafa8">
      <name>Intent.Application.Identity</name>
      <display>Intent.Application.Identity 3.6.1</display>
      <isAbstract>false</isAbstract>
      <value>3.6.1</value>
      <genericTypes />
      <isMapped>false</isMapped>
      <parentFolderId>1f4cee55-0197-49aa-941a-7d4dba029225</parentFolderId>
      <packageId>5d11bab6-4ad1-4ddb-b37f-64c439260fcc</packageId>
      <packageName>Intent.ApplicationTemplate.Aws.Lambda.Functions</packageName>
      <stereotypes />
      <metadata />
      <childElements />
    </childElement>
    <childElement id="a02cdd36-9ca7-4c92-a54a-d9abae228067" type="Module" typeId="6a811790-b322-4340-8b68-84dae5ffafa8">
      <name>Intent.Application.MediatR</name>
      <display>Intent.Application.MediatR 4.5.3</display>
      <isAbstract>false</isAbstract>
      <value>4.5.3</value>
      <genericTypes />
      <isMapped>false</isMapped>
      <parentFolderId>1f4cee55-0197-49aa-941a-7d4dba029225</parentFolderId>
      <packageId>5d11bab6-4ad1-4ddb-b37f-64c439260fcc</packageId>
      <packageName>Intent.ApplicationTemplate.Aws.Lambda.Functions</packageName>
      <stereotypes />
      <metadata />
      <childElements />
    </childElement>
    <childElement id="c142c905-39b2-4617-8f10-71aa073a23ed" type="Module" typeId="6a811790-b322-4340-8b68-84dae5ffafa8">
      <name>Intent.Application.MediatR.Behaviours</name>
      <display>Intent.Application.MediatR.Behaviours 4.5.6</display>
      <isAbstract>false</isAbstract>
      <value>4.5.6</value>
      <genericTypes />
      <isMapped>false</isMapped>
      <parentFolderId>1f4cee55-0197-49aa-941a-7d4dba029225</parentFolderId>
      <packageId>5d11bab6-4ad1-4ddb-b37f-64c439260fcc</packageId>
      <packageName>Intent.ApplicationTemplate.Aws.Lambda.Functions</packageName>
      <stereotypes />
      <metadata />
      <childElements />
    </childElement>
    <childElement id="579b40c0-877b-470a-a6f0-a91adbd285ac" type="Module" typeId="6a811790-b322-4340-8b68-84dae5ffafa8">
      <name>Intent.Application.MediatR.CRUD</name>
      <display>Intent.Application.MediatR.CRUD 7.1.3</display>
      <isAbstract>false</isAbstract>
      <value>7.1.3</value>
      <genericTypes />
      <isMapped>false</isMapped>
      <parentFolderId>1f4cee55-0197-49aa-941a-7d4dba029225</parentFolderId>
      <packageId>5d11bab6-4ad1-4ddb-b37f-64c439260fcc</packageId>
      <packageName>Intent.ApplicationTemplate.Aws.Lambda.Functions</packageName>
      <stereotypes />
      <metadata />
      <childElements />
    </childElement>
    <childElement id="70c7f974-0bb1-4bae-a705-847b30f9b811" type="Module" typeId="6a811790-b322-4340-8b68-84dae5ffafa8">
      <name>Intent.Application.MediatR.CRUD.Eventing</name>
      <display>Intent.Application.MediatR.CRUD.Eventing 5.2.0</display>
      <isAbstract>false</isAbstract>
      <value>5.2.0</value>
      <genericTypes />
      <isMapped>false</isMapped>
      <parentFolderId>1f4cee55-0197-49aa-941a-7d4dba029225</parentFolderId>
      <packageId>5d11bab6-4ad1-4ddb-b37f-64c439260fcc</packageId>
      <packageName>Intent.ApplicationTemplate.Aws.Lambda.Functions</packageName>
      <stereotypes />
      <metadata />
      <childElements />
    </childElement>
    <childElement id="83c3aa84-20b5-4984-b5fd-d1ae299b8d53" type="Module" typeId="6a811790-b322-4340-8b68-84dae5ffafa8">
      <name>Intent.Application.MediatR.CRUD.Tests</name>
      <display>Intent.Application.MediatR.CRUD.Tests 1.3.12</display>
      <isAbstract>false</isAbstract>
      <value>1.3.12</value>
      <genericTypes />
      <isMapped>false</isMapped>
      <parentFolderId>1f4cee55-0197-49aa-941a-7d4dba029225</parentFolderId>
      <packageId>5d11bab6-4ad1-4ddb-b37f-64c439260fcc</packageId>
      <packageName>Intent.ApplicationTemplate.Aws.Lambda.Functions</packageName>
      <stereotypes />
      <metadata />
      <childElements />
    </childElement>
    <childElement id="f43956b8-9e7d-4cb7-b4a8-a32413443baa" type="Module" typeId="6a811790-b322-4340-8b68-84dae5ffafa8">
      <name>Intent.Application.MediatR.FluentValidation</name>
      <display>Intent.Application.MediatR.FluentValidation 4.9.5</display>
      <isAbstract>false</isAbstract>
      <value>4.9.5</value>
      <genericTypes />
      <isMapped>false</isMapped>
      <parentFolderId>1f4cee55-0197-49aa-941a-7d4dba029225</parentFolderId>
      <packageId>5d11bab6-4ad1-4ddb-b37f-64c439260fcc</packageId>
      <packageName>Intent.ApplicationTemplate.Aws.Lambda.Functions</packageName>
      <stereotypes />
      <metadata />
      <childElements />
    </childElement>
    <childElement id="99240b1c-b593-4978-bb35-73a30d16f238" type="Module" typeId="6a811790-b322-4340-8b68-84dae5ffafa8">
      <name>Intent.Application.ServiceImplementations</name>
      <display>Intent.Application.ServiceImplementations 4.5.14</display>
      <isAbstract>false</isAbstract>
      <value>4.5.14</value>
      <genericTypes />
      <isMapped>false</isMapped>
      <parentFolderId>1f4cee55-0197-49aa-941a-7d4dba029225</parentFolderId>
      <packageId>5d11bab6-4ad1-4ddb-b37f-64c439260fcc</packageId>
      <packageName>Intent.ApplicationTemplate.Aws.Lambda.Functions</packageName>
      <stereotypes />
      <metadata />
      <childElements />
    </childElement>
    <childElement id="4279bc34-1f3f-4656-ad27-7c7d4725225f" type="Module" typeId="6a811790-b322-4340-8b68-84dae5ffafa8">
      <name>Intent.Application.ServiceImplementations.CRUD.Eventing</name>
      <display>Intent.Application.ServiceImplementations.CRUD.Eventing 1.1.2</display>
      <isAbstract>false</isAbstract>
      <value>1.1.2</value>
      <genericTypes />
      <isMapped>false</isMapped>
      <parentFolderId>1f4cee55-0197-49aa-941a-7d4dba029225</parentFolderId>
      <packageId>5d11bab6-4ad1-4ddb-b37f-64c439260fcc</packageId>
      <packageName>Intent.ApplicationTemplate.Aws.Lambda.Functions</packageName>
      <stereotypes />
      <metadata />
      <childElements />
    </childElement>
    <childElement id="7548fd65-0c84-466c-b63e-fd92ae3196ff" type="Module" typeId="6a811790-b322-4340-8b68-84dae5ffafa8">
      <name>Intent.AspNetCore</name>
      <display>Intent.AspNetCore 6.1.4</display>
      <isAbstract>false</isAbstract>
      <value>6.1.4</value>
      <genericTypes />
      <isMapped>false</isMapped>
      <parentFolderId>1f4cee55-0197-49aa-941a-7d4dba029225</parentFolderId>
      <packageId>5d11bab6-4ad1-4ddb-b37f-64c439260fcc</packageId>
      <packageName>Intent.ApplicationTemplate.Aws.Lambda.Functions</packageName>
      <stereotypes />
      <metadata />
      <childElements />
    </childElement>
    <childElement id="c2848dac-7222-444c-9aeb-84d4683d46c1" type="Module" typeId="6a811790-b322-4340-8b68-84dae5ffafa8">
      <name>Intent.AspNetCore.Controllers</name>
      <display>Intent.AspNetCore.Controllers 7.1.7</display>
      <isAbstract>false</isAbstract>
      <value>7.1.7</value>
      <genericTypes />
      <isMapped>false</isMapped>
      <parentFolderId>1f4cee55-0197-49aa-941a-7d4dba029225</parentFolderId>
      <packageId>5d11bab6-4ad1-4ddb-b37f-64c439260fcc</packageId>
      <packageName>Intent.ApplicationTemplate.Aws.Lambda.Functions</packageName>
      <stereotypes />
      <metadata />
      <childElements />
    </childElement>
    <childElement id="cef39c50-71ea-4224-92ab-09cdf754b70e" type="Module" typeId="6a811790-b322-4340-8b68-84dae5ffafa8">
      <name>Intent.AspNetCore.Controllers.Dispatch.MediatR</name>
      <display>Intent.AspNetCore.Controllers.Dispatch.MediatR 6.1.2</display>
      <isAbstract>false</isAbstract>
      <value>6.1.2</value>
      <genericTypes />
      <isMapped>false</isMapped>
      <parentFolderId>1f4cee55-0197-49aa-941a-7d4dba029225</parentFolderId>
      <packageId>5d11bab6-4ad1-4ddb-b37f-64c439260fcc</packageId>
      <packageName>Intent.ApplicationTemplate.Aws.Lambda.Functions</packageName>
      <stereotypes />
      <metadata />
      <childElements />
    </childElement>
    <childElement id="fac43e84-15fb-4055-86db-260affa99574" type="Module" typeId="6a811790-b322-4340-8b68-84dae5ffafa8">
      <name>Intent.AspNetCore.Controllers.Dispatch.ServiceContract</name>
      <display>Intent.AspNetCore.Controllers.Dispatch.ServiceContract 5.2.18</display>
      <isAbstract>false</isAbstract>
      <value>5.2.18</value>
      <genericTypes />
      <isMapped>false</isMapped>
      <parentFolderId>1f4cee55-0197-49aa-941a-7d4dba029225</parentFolderId>
      <packageId>5d11bab6-4ad1-4ddb-b37f-64c439260fcc</packageId>
      <packageName>Intent.ApplicationTemplate.Aws.Lambda.Functions</packageName>
      <stereotypes />
      <metadata />
      <childElements />
    </childElement>
    <childElement id="d3fb8427-79af-4edd-87f3-864e460b310f" type="Module" typeId="6a811790-b322-4340-8b68-84dae5ffafa8">
      <name>Intent.AspNetCore.Grpc</name>
      <display>Intent.AspNetCore.Grpc 1.0.1</display>
      <isAbstract>false</isAbstract>
      <value>1.0.1</value>
      <genericTypes />
      <isMapped>false</isMapped>
      <parentFolderId>1f4cee55-0197-49aa-941a-7d4dba029225</parentFolderId>
      <packageId>5d11bab6-4ad1-4ddb-b37f-64c439260fcc</packageId>
      <packageName>Intent.ApplicationTemplate.Aws.Lambda.Functions</packageName>
      <stereotypes />
      <metadata />
      <childElements />
    </childElement>
    <childElement id="8ffaee32-54e8-4461-a172-cee154bedda6" type="Module" typeId="6a811790-b322-4340-8b68-84dae5ffafa8">
      <name>Intent.AspNetCore.HealthChecks</name>
      <display>Intent.AspNetCore.HealthChecks 2.0.13</display>
      <isAbstract>false</isAbstract>
      <value>2.0.13</value>
      <genericTypes />
      <isMapped>false</isMapped>
      <parentFolderId>1f4cee55-0197-49aa-941a-7d4dba029225</parentFolderId>
      <packageId>5d11bab6-4ad1-4ddb-b37f-64c439260fcc</packageId>
      <packageName>Intent.ApplicationTemplate.Aws.Lambda.Functions</packageName>
      <stereotypes />
      <metadata />
      <childElements />
    </childElement>
    <childElement id="0d00279e-d5e1-4616-9ef3-37edac33c726" type="Module" typeId="6a811790-b322-4340-8b68-84dae5ffafa8">
      <name>Intent.AspNetCore.Interop.Angular</name>
      <display>Intent.AspNetCore.Interop.Angular 4.0.3</display>
      <isAbstract>false</isAbstract>
      <value>4.0.3</value>
      <genericTypes />
      <isMapped>false</isMapped>
      <parentFolderId>1f4cee55-0197-49aa-941a-7d4dba029225</parentFolderId>
      <packageId>5d11bab6-4ad1-4ddb-b37f-64c439260fcc</packageId>
      <packageName>Intent.ApplicationTemplate.Aws.Lambda.Functions</packageName>
      <stereotypes />
      <metadata />
      <childElements />
    </childElement>
    <childElement id="5e2b2ae5-7af0-480f-bcec-c60619d9bbf7" type="Module" typeId="6a811790-b322-4340-8b68-84dae5ffafa8">
      <name>Intent.AspNetCore.Mvc</name>
      <display>Intent.AspNetCore.Mvc 1.0.0-beta.10</display>
      <isAbstract>false</isAbstract>
      <value>1.0.0-beta.10</value>
      <genericTypes />
      <isMapped>false</isMapped>
      <parentFolderId>1f4cee55-0197-49aa-941a-7d4dba029225</parentFolderId>
      <packageId>5d11bab6-4ad1-4ddb-b37f-64c439260fcc</packageId>
      <packageName>Intent.ApplicationTemplate.Aws.Lambda.Functions</packageName>
      <stereotypes />
      <metadata />
      <childElements />
    </childElement>
    <childElement id="15e42098-91d4-4d36-9d83-f5f053bae88e" type="Module" typeId="6a811790-b322-4340-8b68-84dae5ffafa8">
      <name>Intent.AspNetCore.SignalR</name>
      <display>Intent.AspNetCore.SignalR 1.0.8</display>
      <isAbstract>false</isAbstract>
      <value>1.0.8</value>
      <genericTypes />
      <isMapped>false</isMapped>
      <parentFolderId>1f4cee55-0197-49aa-941a-7d4dba029225</parentFolderId>
      <packageId>5d11bab6-4ad1-4ddb-b37f-64c439260fcc</packageId>
      <packageName>Intent.ApplicationTemplate.Aws.Lambda.Functions</packageName>
      <stereotypes />
      <metadata />
      <childElements />
    </childElement>
    <childElement id="8f87fc08-4655-4983-bec5-85b08a955590" type="Module" typeId="6a811790-b322-4340-8b68-84dae5ffafa8">
      <name>Intent.AspNetCore.Swashbuckle</name>
      <display>Intent.AspNetCore.Swashbuckle 5.2.1</display>
      <isAbstract>false</isAbstract>
      <value>5.2.1</value>
      <genericTypes />
      <isMapped>false</isMapped>
      <parentFolderId>1f4cee55-0197-49aa-941a-7d4dba029225</parentFolderId>
      <packageId>5d11bab6-4ad1-4ddb-b37f-64c439260fcc</packageId>
      <packageName>Intent.ApplicationTemplate.Aws.Lambda.Functions</packageName>
      <stereotypes />
      <metadata />
      <childElements />
    </childElement>
    <childElement id="d930e420-d416-4199-b241-9fccbc7822cf" type="Module" typeId="6a811790-b322-4340-8b68-84dae5ffafa8">
      <name>Intent.AspNetCore.Swashbuckle.Security</name>
      <display>Intent.AspNetCore.Swashbuckle.Security 4.0.11</display>
      <isAbstract>false</isAbstract>
      <value>4.0.11</value>
      <genericTypes />
      <isMapped>false</isMapped>
      <parentFolderId>1f4cee55-0197-49aa-941a-7d4dba029225</parentFolderId>
      <packageId>5d11bab6-4ad1-4ddb-b37f-64c439260fcc</packageId>
      <packageName>Intent.ApplicationTemplate.Aws.Lambda.Functions</packageName>
      <stereotypes />
      <metadata />
      <childElements />
    </childElement>
    <childElement id="1f96bb15-09d0-4128-8051-b1a12f7de6a6" type="Module" typeId="6a811790-b322-4340-8b68-84dae5ffafa8">
      <name>Intent.Aws.Common</name>
      <display>Intent.Aws.Common 1.0.5</display>
      <isAbstract>false</isAbstract>
      <value>1.0.5</value>
      <genericTypes />
      <isMapped>false</isMapped>
      <parentFolderId>1f4cee55-0197-49aa-941a-7d4dba029225</parentFolderId>
      <packageId>5d11bab6-4ad1-4ddb-b37f-64c439260fcc</packageId>
      <packageName>Intent.ApplicationTemplate.Aws.Lambda.Functions</packageName>
      <stereotypes />
      <metadata />
      <childElements />
    </childElement>
    <childElement id="3d5e078a-2e44-4570-9b25-93b83d5d7695" type="Module" typeId="6a811790-b322-4340-8b68-84dae5ffafa8">
      <name>Intent.Aws.Lambda.Functions</name>
      <display>Intent.Aws.Lambda.Functions 1.0.4</display>
      <isAbstract>false</isAbstract>
      <value>1.0.4</value>
      <genericTypes />
      <isMapped>false</isMapped>
      <parentFolderId>1f4cee55-0197-49aa-941a-7d4dba029225</parentFolderId>
      <packageId>5d11bab6-4ad1-4ddb-b37f-64c439260fcc</packageId>
      <packageName>Intent.ApplicationTemplate.Aws.Lambda.Functions</packageName>
      <stereotypes />
      <metadata />
      <childElements />
    </childElement>
    <childElement id="17ad00df-8a0b-4953-b37f-44b89d52dbfb" type="Module" typeId="6a811790-b322-4340-8b68-84dae5ffafa8">
      <name>Intent.Aws.Lambda.Functions.Dispatch.MediatR</name>
      <display>Intent.Aws.Lambda.Functions.Dispatch.MediatR 1.0.1</display>
      <isAbstract>false</isAbstract>
      <value>1.0.1</value>
      <genericTypes />
      <isMapped>false</isMapped>
      <parentFolderId>1f4cee55-0197-49aa-941a-7d4dba029225</parentFolderId>
      <packageId>5d11bab6-4ad1-4ddb-b37f-64c439260fcc</packageId>
      <packageName>Intent.ApplicationTemplate.Aws.Lambda.Functions</packageName>
      <stereotypes />
      <metadata />
      <childElements />
    </childElement>
    <childElement id="81a97069-2a41-402a-8e1c-f6dea985fefe" type="Module" typeId="6a811790-b322-4340-8b68-84dae5ffafa8">
      <name>Intent.Aws.Lambda.Functions.Dispatch.Services</name>
      <display>Intent.Aws.Lambda.Functions.Dispatch.Services 1.0.1</display>
      <isAbstract>false</isAbstract>
      <value>1.0.1</value>
      <genericTypes />
      <isMapped>false</isMapped>
      <parentFolderId>1f4cee55-0197-49aa-941a-7d4dba029225</parentFolderId>
      <packageId>5d11bab6-4ad1-4ddb-b37f-64c439260fcc</packageId>
      <packageName>Intent.ApplicationTemplate.Aws.Lambda.Functions</packageName>
      <stereotypes />
      <metadata />
      <childElements />
    </childElement>
    <childElement id="e0730248-32f4-49f3-ab1d-88d273cceeb5" type="Module" typeId="6a811790-b322-4340-8b68-84dae5ffafa8">
      <name>Intent.Aws.Lambda.Functions.Sqs</name>
      <display>Intent.Aws.Lambda.Functions.Sqs 1.0.0</display>
      <isAbstract>false</isAbstract>
      <value>1.0.0</value>
      <genericTypes />
      <isMapped>false</isMapped>
      <parentFolderId>1f4cee55-0197-49aa-941a-7d4dba029225</parentFolderId>
      <packageId>5d11bab6-4ad1-4ddb-b37f-64c439260fcc</packageId>
      <packageName>Intent.ApplicationTemplate.Aws.Lambda.Functions</packageName>
      <stereotypes />
      <metadata />
      <childElements />
    </childElement>
    <childElement id="e118a3e1-50db-4543-a3a1-8a85ba3c2100" type="Module" typeId="6a811790-b322-4340-8b68-84dae5ffafa8">
      <name>Intent.Aws.Sqs</name>
      <display>Intent.Aws.Sqs 1.0.2</display>
      <isAbstract>false</isAbstract>
      <value>1.0.2</value>
      <genericTypes />
      <isMapped>false</isMapped>
      <parentFolderId>1f4cee55-0197-49aa-941a-7d4dba029225</parentFolderId>
      <packageId>5d11bab6-4ad1-4ddb-b37f-64c439260fcc</packageId>
      <packageName>Intent.ApplicationTemplate.Aws.Lambda.Functions</packageName>
      <stereotypes />
      <metadata />
      <childElements />
    </childElement>
    <childElement id="7ef0e04d-8de1-4ab3-a5c0-c401129445a3" type="Module" typeId="6a811790-b322-4340-8b68-84dae5ffafa8">
      <name>Intent.Azure.KeyVault</name>
      <display>Intent.Azure.KeyVault 2.0.18</display>
      <isAbstract>false</isAbstract>
      <value>2.0.18</value>
      <genericTypes />
      <isMapped>false</isMapped>
      <parentFolderId>1f4cee55-0197-49aa-941a-7d4dba029225</parentFolderId>
      <packageId>5d11bab6-4ad1-4ddb-b37f-64c439260fcc</packageId>
      <packageName>Intent.ApplicationTemplate.Aws.Lambda.Functions</packageName>
      <stereotypes />
      <metadata />
      <childElements />
    </childElement>
    <childElement id="01e73b17-a13d-4088-aab6-e614eb138403" type="Module" typeId="6a811790-b322-4340-8b68-84dae5ffafa8">
      <name>Intent.Azure.TableStorage</name>
      <display>Intent.Azure.TableStorage 1.0.0-beta.31</display>
      <isAbstract>false</isAbstract>
      <value>1.0.0-beta.31</value>
      <genericTypes />
      <isMapped>false</isMapped>
      <parentFolderId>1f4cee55-0197-49aa-941a-7d4dba029225</parentFolderId>
      <packageId>5d11bab6-4ad1-4ddb-b37f-64c439260fcc</packageId>
      <packageName>Intent.ApplicationTemplate.Aws.Lambda.Functions</packageName>
      <stereotypes />
      <metadata />
      <childElements />
    </childElement>
    <childElement id="86bb1241-672a-4e38-894d-9ef4dc23bcb3" type="Module" typeId="6a811790-b322-4340-8b68-84dae5ffafa8">
      <name>Intent.AzureFunctions</name>
      <display>Intent.AzureFunctions 5.0.21</display>
      <isAbstract>false</isAbstract>
      <value>5.0.21</value>
      <genericTypes />
      <isMapped>false</isMapped>
      <parentFolderId>1f4cee55-0197-49aa-941a-7d4dba029225</parentFolderId>
      <packageId>5d11bab6-4ad1-4ddb-b37f-64c439260fcc</packageId>
      <packageName>Intent.ApplicationTemplate.Aws.Lambda.Functions</packageName>
      <stereotypes />
      <metadata />
      <childElements />
    </childElement>
    <childElement id="d9b9a8d9-b904-4dd7-a09a-12adfdc7e4ab" type="Module" typeId="6a811790-b322-4340-8b68-84dae5ffafa8">
      <name>Intent.AzureFunctions.AzureEventGrid</name>
      <display>Intent.AzureFunctions.AzureEventGrid 1.1.5</display>
      <isAbstract>false</isAbstract>
      <value>1.1.5</value>
      <genericTypes />
      <isMapped>false</isMapped>
      <parentFolderId>1f4cee55-0197-49aa-941a-7d4dba029225</parentFolderId>
      <packageId>5d11bab6-4ad1-4ddb-b37f-64c439260fcc</packageId>
      <packageName>Intent.ApplicationTemplate.Aws.Lambda.Functions</packageName>
      <stereotypes />
      <metadata />
      <childElements />
    </childElement>
    <childElement id="0e401625-b6a8-4926-9b9b-a597e781088e" type="Module" typeId="6a811790-b322-4340-8b68-84dae5ffafa8">
      <name>Intent.AzureFunctions.AzureServiceBus</name>
      <display>Intent.AzureFunctions.AzureServiceBus 1.0.8</display>
      <isAbstract>false</isAbstract>
      <value>1.0.8</value>
      <genericTypes />
      <isMapped>false</isMapped>
      <parentFolderId>1f4cee55-0197-49aa-941a-7d4dba029225</parentFolderId>
      <packageId>5d11bab6-4ad1-4ddb-b37f-64c439260fcc</packageId>
      <packageName>Intent.ApplicationTemplate.Aws.Lambda.Functions</packageName>
      <stereotypes />
      <metadata />
      <childElements />
    </childElement>
    <childElement id="bb5f8d68-96ec-46a6-9e41-83c5a31a9fed" type="Module" typeId="6a811790-b322-4340-8b68-84dae5ffafa8">
      <name>Intent.AzureFunctions.Dispatch.MediatR</name>
      <display>Intent.AzureFunctions.Dispatch.MediatR 2.0.4</display>
      <isAbstract>false</isAbstract>
      <value>2.0.4</value>
      <genericTypes />
      <isMapped>false</isMapped>
      <parentFolderId>1f4cee55-0197-49aa-941a-7d4dba029225</parentFolderId>
      <packageId>5d11bab6-4ad1-4ddb-b37f-64c439260fcc</packageId>
      <packageName>Intent.ApplicationTemplate.Aws.Lambda.Functions</packageName>
      <stereotypes />
      <metadata />
      <childElements />
    </childElement>
    <childElement id="5be3205c-8026-43b2-98a1-1181300e44ca" type="Module" typeId="6a811790-b322-4340-8b68-84dae5ffafa8">
      <name>Intent.AzureFunctions.Dispatch.Services</name>
      <display>Intent.AzureFunctions.Dispatch.Services 5.0.4</display>
      <isAbstract>false</isAbstract>
      <value>5.0.4</value>
      <genericTypes />
      <isMapped>false</isMapped>
      <parentFolderId>1f4cee55-0197-49aa-941a-7d4dba029225</parentFolderId>
      <packageId>5d11bab6-4ad1-4ddb-b37f-64c439260fcc</packageId>
      <packageName>Intent.ApplicationTemplate.Aws.Lambda.Functions</packageName>
      <stereotypes />
      <metadata />
      <childElements />
    </childElement>
    <childElement id="d807ad21-296a-4056-84aa-84dd20803ddd" type="Module" typeId="6a811790-b322-4340-8b68-84dae5ffafa8">
      <name>Intent.AzureFunctions.FluentValidation</name>
      <display>Intent.AzureFunctions.FluentValidation 5.1.3</display>
      <isAbstract>false</isAbstract>
      <value>5.1.3</value>
      <genericTypes />
      <isMapped>false</isMapped>
      <parentFolderId>1f4cee55-0197-49aa-941a-7d4dba029225</parentFolderId>
      <packageId>5d11bab6-4ad1-4ddb-b37f-64c439260fcc</packageId>
      <packageName>Intent.ApplicationTemplate.Aws.Lambda.Functions</packageName>
      <stereotypes />
      <metadata />
      <childElements />
    </childElement>
    <childElement id="a65aecb2-215b-47f0-ac07-2f53daab2196" type="Module" typeId="6a811790-b322-4340-8b68-84dae5ffafa8">
      <name>Intent.AzureFunctions.OpenApi</name>
      <display>Intent.AzureFunctions.OpenApi 2.0.9</display>
      <isAbstract>false</isAbstract>
      <value>2.0.9</value>
      <genericTypes />
      <isMapped>false</isMapped>
      <parentFolderId>1f4cee55-0197-49aa-941a-7d4dba029225</parentFolderId>
      <packageId>5d11bab6-4ad1-4ddb-b37f-64c439260fcc</packageId>
      <packageName>Intent.ApplicationTemplate.Aws.Lambda.Functions</packageName>
      <stereotypes />
      <metadata />
      <childElements />
    </childElement>
    <childElement id="c76cb53d-cbb8-426a-8d18-81607357a059" type="Module" typeId="6a811790-b322-4340-8b68-84dae5ffafa8">
      <name>Intent.Blazor</name>
      <display>Intent.Blazor 1.0.7</display>
      <isAbstract>false</isAbstract>
      <value>1.0.7</value>
      <genericTypes />
      <isMapped>false</isMapped>
      <parentFolderId>1f4cee55-0197-49aa-941a-7d4dba029225</parentFolderId>
      <packageId>5d11bab6-4ad1-4ddb-b37f-64c439260fcc</packageId>
      <packageName>Intent.ApplicationTemplate.Aws.Lambda.Functions</packageName>
      <stereotypes />
      <metadata />
      <childElements />
    </childElement>
    <childElement id="350cce99-f79d-4ada-a153-45ec7f5f2d79" type="Module" typeId="6a811790-b322-4340-8b68-84dae5ffafa8">
      <name>Intent.Blazor.Components.MudBlazor</name>
      <display>Intent.Blazor.Components.MudBlazor 1.0.6</display>
      <isAbstract>false</isAbstract>
      <value>1.0.6</value>
      <genericTypes />
      <isMapped>false</isMapped>
      <parentFolderId>1f4cee55-0197-49aa-941a-7d4dba029225</parentFolderId>
      <packageId>5d11bab6-4ad1-4ddb-b37f-64c439260fcc</packageId>
      <packageName>Intent.ApplicationTemplate.Aws.Lambda.Functions</packageName>
      <stereotypes />
      <metadata />
      <childElements />
    </childElement>
    <childElement id="748d8a82-70d1-4601-bb6b-a996cd5c8e6c" type="Module" typeId="6a811790-b322-4340-8b68-84dae5ffafa8">
      <name>Intent.Code.Weaving.Json</name>
      <display>Intent.Code.Weaving.Json 1.0.1</display>
      <isAbstract>false</isAbstract>
      <value>1.0.1</value>
      <genericTypes />
      <isMapped>false</isMapped>
      <parentFolderId>1f4cee55-0197-49aa-941a-7d4dba029225</parentFolderId>
      <packageId>5d11bab6-4ad1-4ddb-b37f-64c439260fcc</packageId>
      <packageName>Intent.ApplicationTemplate.Aws.Lambda.Functions</packageName>
      <stereotypes />
      <metadata />
      <childElements />
    </childElement>
    <childElement id="7811fd06-a4ce-42c6-a074-f15462475b67" type="Module" typeId="6a811790-b322-4340-8b68-84dae5ffafa8">
      <name>Intent.Code.Weaving.Razor</name>
      <display>Intent.Code.Weaving.Razor 2.0.3</display>
      <isAbstract>false</isAbstract>
      <value>2.0.3</value>
      <genericTypes />
      <isMapped>false</isMapped>
      <parentFolderId>1f4cee55-0197-49aa-941a-7d4dba029225</parentFolderId>
      <packageId>5d11bab6-4ad1-4ddb-b37f-64c439260fcc</packageId>
      <packageName>Intent.ApplicationTemplate.Aws.Lambda.Functions</packageName>
      <stereotypes />
      <metadata />
      <childElements />
    </childElement>
    <childElement id="647fcf94-a0f8-48b4-94d5-65cf5f04ecfa" type="Module" typeId="6a811790-b322-4340-8b68-84dae5ffafa8">
      <name>Intent.Common</name>
      <display>Intent.Common 3.9.2</display>
      <isAbstract>false</isAbstract>
      <value>3.9.2</value>
      <genericTypes />
      <isMapped>false</isMapped>
      <parentFolderId>1f4cee55-0197-49aa-941a-7d4dba029225</parentFolderId>
      <packageId>5d11bab6-4ad1-4ddb-b37f-64c439260fcc</packageId>
      <packageName>Intent.ApplicationTemplate.Aws.Lambda.Functions</packageName>
      <stereotypes />
      <metadata />
      <childElements />
    </childElement>
    <childElement id="d2e3240c-7751-45a3-ae26-a5c64f88e3e3" type="Module" typeId="6a811790-b322-4340-8b68-84dae5ffafa8">
      <name>Intent.Common.AI</name>
      <display>Intent.Common.AI 1.0.0-beta.14</display>
      <isAbstract>false</isAbstract>
      <value>1.0.0-beta.14</value>
      <genericTypes />
      <isMapped>false</isMapped>
      <parentFolderId>1f4cee55-0197-49aa-941a-7d4dba029225</parentFolderId>
      <packageId>5d11bab6-4ad1-4ddb-b37f-64c439260fcc</packageId>
      <packageName>Intent.ApplicationTemplate.Aws.Lambda.Functions</packageName>
      <stereotypes />
      <metadata />
      <childElements />
    </childElement>
    <childElement id="da31f6a8-8ca0-4692-9974-68f4a781516d" type="Module" typeId="6a811790-b322-4340-8b68-84dae5ffafa8">
      <name>Intent.Common.CSharp</name>
      <display>Intent.Common.CSharp 3.9.11</display>
      <isAbstract>false</isAbstract>
      <value>3.9.11</value>
      <genericTypes />
      <isMapped>false</isMapped>
      <parentFolderId>1f4cee55-0197-49aa-941a-7d4dba029225</parentFolderId>
      <packageId>5d11bab6-4ad1-4ddb-b37f-64c439260fcc</packageId>
      <packageName>Intent.ApplicationTemplate.Aws.Lambda.Functions</packageName>
      <stereotypes />
      <metadata />
      <childElements />
    </childElement>
    <childElement id="f49cc984-870f-4f25-b475-cedf464f836b" type="Module" typeId="6a811790-b322-4340-8b68-84dae5ffafa8">
      <name>Intent.Common.Types</name>
      <display>Intent.Common.Types 4.1.2</display>
      <isAbstract>false</isAbstract>
      <value>4.1.2</value>
      <genericTypes />
      <isMapped>false</isMapped>
      <parentFolderId>1f4cee55-0197-49aa-941a-7d4dba029225</parentFolderId>
      <packageId>5d11bab6-4ad1-4ddb-b37f-64c439260fcc</packageId>
      <packageName>Intent.ApplicationTemplate.Aws.Lambda.Functions</packageName>
      <stereotypes />
      <metadata />
      <childElements />
    </childElement>
    <childElement id="f288a9d4-8037-441b-9f74-9efd1909f1a7" type="Module" typeId="6a811790-b322-4340-8b68-84dae5ffafa8">
      <name>Intent.Common.UnitOfWork</name>
      <display>Intent.Common.UnitOfWork 1.0.3</display>
      <isAbstract>false</isAbstract>
      <value>1.0.3</value>
      <genericTypes />
      <isMapped>false</isMapped>
      <parentFolderId>1f4cee55-0197-49aa-941a-7d4dba029225</parentFolderId>
      <packageId>5d11bab6-4ad1-4ddb-b37f-64c439260fcc</packageId>
      <packageName>Intent.ApplicationTemplate.Aws.Lambda.Functions</packageName>
      <stereotypes />
      <metadata />
      <childElements />
    </childElement>
    <childElement id="e14b75e1-5e64-48f9-9a9d-b8a86bafe253" type="Module" typeId="6a811790-b322-4340-8b68-84dae5ffafa8">
      <name>Intent.CosmosDB</name>
      <display>Intent.CosmosDB 1.2.23</display>
      <isAbstract>false</isAbstract>
      <value>1.2.23</value>
      <genericTypes />
      <isMapped>false</isMapped>
      <parentFolderId>1f4cee55-0197-49aa-941a-7d4dba029225</parentFolderId>
      <packageId>5d11bab6-4ad1-4ddb-b37f-64c439260fcc</packageId>
      <packageName>Intent.ApplicationTemplate.Aws.Lambda.Functions</packageName>
      <stereotypes />
      <metadata />
      <childElements />
    </childElement>
    <childElement id="dde76598-9719-4188-a0f7-4d0f8779f2e4" type="Module" typeId="6a811790-b322-4340-8b68-84dae5ffafa8">
      <name>Intent.Dapr.AspNetCore</name>
      <display>Intent.Dapr.AspNetCore 2.0.13</display>
      <isAbstract>false</isAbstract>
      <value>2.0.13</value>
      <genericTypes />
      <isMapped>false</isMapped>
      <parentFolderId>1f4cee55-0197-49aa-941a-7d4dba029225</parentFolderId>
      <packageId>5d11bab6-4ad1-4ddb-b37f-64c439260fcc</packageId>
      <packageName>Intent.ApplicationTemplate.Aws.Lambda.Functions</packageName>
      <stereotypes />
      <metadata />
      <childElements />
    </childElement>
    <childElement id="068bbc37-f2a5-4a50-bab8-4c43d3422b00" type="Module" typeId="6a811790-b322-4340-8b68-84dae5ffafa8">
      <name>Intent.Dapr.AspNetCore.Configuration</name>
      <display>Intent.Dapr.AspNetCore.Configuration 1.1.8</display>
      <isAbstract>false</isAbstract>
      <value>1.1.8</value>
      <genericTypes />
      <isMapped>false</isMapped>
      <parentFolderId>1f4cee55-0197-49aa-941a-7d4dba029225</parentFolderId>
      <packageId>5d11bab6-4ad1-4ddb-b37f-64c439260fcc</packageId>
      <packageName>Intent.ApplicationTemplate.Aws.Lambda.Functions</packageName>
      <stereotypes />
      <metadata />
      <childElements />
    </childElement>
    <childElement id="23d936b8-186f-4f57-88f8-3d92c7d6ddf3" type="Module" typeId="6a811790-b322-4340-8b68-84dae5ffafa8">
      <name>Intent.Dapr.AspNetCore.Pubsub</name>
      <display>Intent.Dapr.AspNetCore.Pubsub 3.0.9</display>
      <isAbstract>false</isAbstract>
      <value>3.0.9</value>
      <genericTypes />
      <isMapped>false</isMapped>
      <parentFolderId>1f4cee55-0197-49aa-941a-7d4dba029225</parentFolderId>
      <packageId>5d11bab6-4ad1-4ddb-b37f-64c439260fcc</packageId>
      <packageName>Intent.ApplicationTemplate.Aws.Lambda.Functions</packageName>
      <stereotypes />
      <metadata />
      <childElements />
    </childElement>
    <childElement id="d39e33a3-2839-40f8-b055-cbefb10e5275" type="Module" typeId="6a811790-b322-4340-8b68-84dae5ffafa8">
      <name>Intent.Dapr.AspNetCore.Secrets</name>
      <display>Intent.Dapr.AspNetCore.Secrets 1.1.8</display>
      <isAbstract>false</isAbstract>
      <value>1.1.8</value>
      <genericTypes />
      <isMapped>false</isMapped>
      <parentFolderId>1f4cee55-0197-49aa-941a-7d4dba029225</parentFolderId>
      <packageId>5d11bab6-4ad1-4ddb-b37f-64c439260fcc</packageId>
      <packageName>Intent.ApplicationTemplate.Aws.Lambda.Functions</packageName>
      <stereotypes />
      <metadata />
      <childElements />
    </childElement>
    <childElement id="30a5d173-9cc7-4707-9d97-a5d5923dacad" type="Module" typeId="6a811790-b322-4340-8b68-84dae5ffafa8">
      <name>Intent.Dapr.AspNetCore.ServiceInvocation</name>
      <display>Intent.Dapr.AspNetCore.ServiceInvocation 2.2.29</display>
      <isAbstract>false</isAbstract>
      <value>2.2.29</value>
      <genericTypes />
      <isMapped>false</isMapped>
      <parentFolderId>1f4cee55-0197-49aa-941a-7d4dba029225</parentFolderId>
      <packageId>5d11bab6-4ad1-4ddb-b37f-64c439260fcc</packageId>
      <packageName>Intent.ApplicationTemplate.Aws.Lambda.Functions</packageName>
      <stereotypes />
      <metadata />
      <childElements />
    </childElement>
    <childElement id="f315d73f-def8-434a-8e28-79c104cd83c1" type="Module" typeId="6a811790-b322-4340-8b68-84dae5ffafa8">
      <name>Intent.Dapr.AspNetCore.StateManagement</name>
      <display>Intent.Dapr.AspNetCore.StateManagement 1.2.16</display>
      <isAbstract>false</isAbstract>
      <value>1.2.16</value>
      <genericTypes />
      <isMapped>false</isMapped>
      <parentFolderId>1f4cee55-0197-49aa-941a-7d4dba029225</parentFolderId>
      <packageId>5d11bab6-4ad1-4ddb-b37f-64c439260fcc</packageId>
      <packageName>Intent.ApplicationTemplate.Aws.Lambda.Functions</packageName>
      <stereotypes />
      <metadata />
      <childElements />
    </childElement>
    <childElement id="6f2089f4-3262-4879-8838-05a86d1aa709" type="Module" typeId="6a811790-b322-4340-8b68-84dae5ffafa8">
      <name>Intent.DocumentDB.Dtos.AutoMapper</name>
      <display>Intent.DocumentDB.Dtos.AutoMapper 1.0.6</display>
      <isAbstract>false</isAbstract>
      <value>1.0.6</value>
      <genericTypes />
      <isMapped>false</isMapped>
      <parentFolderId>1f4cee55-0197-49aa-941a-7d4dba029225</parentFolderId>
      <packageId>5d11bab6-4ad1-4ddb-b37f-64c439260fcc</packageId>
      <packageName>Intent.ApplicationTemplate.Aws.Lambda.Functions</packageName>
      <stereotypes />
      <metadata />
      <childElements />
    </childElement>
    <childElement id="aac60f9c-803e-4979-a896-a8b5fa6e0b13" type="Module" typeId="6a811790-b322-4340-8b68-84dae5ffafa8">
      <name>Intent.DomainEvents</name>
      <display>Intent.DomainEvents 5.0.12</display>
      <isAbstract>false</isAbstract>
      <value>5.0.12</value>
      <genericTypes />
      <isMapped>false</isMapped>
      <parentFolderId>1f4cee55-0197-49aa-941a-7d4dba029225</parentFolderId>
      <packageId>5d11bab6-4ad1-4ddb-b37f-64c439260fcc</packageId>
      <packageName>Intent.ApplicationTemplate.Aws.Lambda.Functions</packageName>
      <stereotypes />
      <metadata />
      <childElements />
    </childElement>
    <childElement id="1a29d7e9-50eb-4ba4-adad-94166a4bc3e2" type="Module" typeId="6a811790-b322-4340-8b68-84dae5ffafa8">
      <name>Intent.Entities</name>
      <display>Intent.Entities 5.1.15</display>
      <isAbstract>false</isAbstract>
      <value>5.1.15</value>
      <genericTypes />
      <isMapped>false</isMapped>
      <parentFolderId>1f4cee55-0197-49aa-941a-7d4dba029225</parentFolderId>
      <packageId>5d11bab6-4ad1-4ddb-b37f-64c439260fcc</packageId>
      <packageName>Intent.ApplicationTemplate.Aws.Lambda.Functions</packageName>
      <stereotypes />
      <metadata />
      <childElements />
    </childElement>
    <childElement id="a3f929b8-a15a-4ac7-be32-518422a9286e" type="Module" typeId="6a811790-b322-4340-8b68-84dae5ffafa8">
      <name>Intent.Entities.Constants</name>
      <display>Intent.Entities.Constants 1.0.6</display>
      <isAbstract>false</isAbstract>
      <value>1.0.6</value>
      <genericTypes />
      <isMapped>false</isMapped>
      <parentFolderId>1f4cee55-0197-49aa-941a-7d4dba029225</parentFolderId>
      <packageId>5d11bab6-4ad1-4ddb-b37f-64c439260fcc</packageId>
      <packageName>Intent.ApplicationTemplate.Aws.Lambda.Functions</packageName>
      <stereotypes />
      <metadata />
      <childElements />
    </childElement>
    <childElement id="ef260ab6-5b2c-4674-b610-31a7f8de7d19" type="Module" typeId="6a811790-b322-4340-8b68-84dae5ffafa8">
      <name>Intent.Entities.Repositories.Api</name>
      <display>Intent.Entities.Repositories.Api 5.1.10</display>
      <isAbstract>false</isAbstract>
      <value>5.1.10</value>
      <genericTypes />
      <isMapped>false</isMapped>
      <parentFolderId>1f4cee55-0197-49aa-941a-7d4dba029225</parentFolderId>
      <packageId>5d11bab6-4ad1-4ddb-b37f-64c439260fcc</packageId>
      <packageName>Intent.ApplicationTemplate.Aws.Lambda.Functions</packageName>
      <stereotypes />
      <metadata />
      <childElements />
    </childElement>
    <childElement id="be9c5214-bd90-46fd-b3b6-b22f25e0d9ff" type="Module" typeId="6a811790-b322-4340-8b68-84dae5ffafa8">
      <name>Intent.EntityFrameworkCore</name>
      <display>Intent.EntityFrameworkCore 5.0.34</display>
      <isAbstract>false</isAbstract>
      <value>5.0.34</value>
      <genericTypes />
      <isMapped>false</isMapped>
      <parentFolderId>1f4cee55-0197-49aa-941a-7d4dba029225</parentFolderId>
      <packageId>5d11bab6-4ad1-4ddb-b37f-64c439260fcc</packageId>
      <packageName>Intent.ApplicationTemplate.Aws.Lambda.Functions</packageName>
      <stereotypes />
      <metadata />
      <childElements />
    </childElement>
    <childElement id="c7b372d8-4ec8-43e4-a7c3-22a4b7afe22d" type="Module" typeId="6a811790-b322-4340-8b68-84dae5ffafa8">
      <name>Intent.EntityFrameworkCore.DesignTimeDbContextFactory</name>
      <display>Intent.EntityFrameworkCore.DesignTimeDbContextFactory 4.2.15</display>
      <isAbstract>false</isAbstract>
      <value>4.2.15</value>
      <genericTypes />
      <isMapped>false</isMapped>
      <parentFolderId>1f4cee55-0197-49aa-941a-7d4dba029225</parentFolderId>
      <packageId>5d11bab6-4ad1-4ddb-b37f-64c439260fcc</packageId>
      <packageName>Intent.ApplicationTemplate.Aws.Lambda.Functions</packageName>
      <stereotypes />
      <metadata />
      <childElements />
    </childElement>
    <childElement id="88f6b327-1ca4-4ea6-8d35-d8ba2855432c" type="Module" typeId="6a811790-b322-4340-8b68-84dae5ffafa8">
      <name>Intent.EntityFrameworkCore.Interop.DomainEvents</name>
      <display>Intent.EntityFrameworkCore.Interop.DomainEvents 4.1.4</display>
      <isAbstract>false</isAbstract>
      <value>4.1.4</value>
      <genericTypes />
      <isMapped>false</isMapped>
      <parentFolderId>1f4cee55-0197-49aa-941a-7d4dba029225</parentFolderId>
      <packageId>5d11bab6-4ad1-4ddb-b37f-64c439260fcc</packageId>
      <packageName>Intent.ApplicationTemplate.Aws.Lambda.Functions</packageName>
      <stereotypes />
      <metadata />
      <childElements />
    </childElement>
    <childElement id="dce1fb3e-6943-4fdb-b43a-225036177e9d" type="Module" typeId="6a811790-b322-4340-8b68-84dae5ffafa8">
      <name>Intent.EntityFrameworkCore.Repositories</name>
      <display>Intent.EntityFrameworkCore.Repositories 4.7.17</display>
      <isAbstract>false</isAbstract>
      <value>4.7.17</value>
      <genericTypes />
      <isMapped>false</isMapped>
      <parentFolderId>1f4cee55-0197-49aa-941a-7d4dba029225</parentFolderId>
      <packageId>5d11bab6-4ad1-4ddb-b37f-64c439260fcc</packageId>
      <packageName>Intent.ApplicationTemplate.Aws.Lambda.Functions</packageName>
      <stereotypes />
      <metadata />
      <childElements />
    </childElement>
    <childElement id="efb9c334-6033-4df9-aaec-1f9b8ca8a04d" type="Module" typeId="6a811790-b322-4340-8b68-84dae5ffafa8">
      <name>Intent.Eventing.AzureEventGrid</name>
      <display>Intent.Eventing.AzureEventGrid 1.2.3</display>
      <isAbstract>false</isAbstract>
      <value>1.2.3</value>
      <genericTypes />
      <isMapped>false</isMapped>
      <parentFolderId>1f4cee55-0197-49aa-941a-7d4dba029225</parentFolderId>
      <packageId>5d11bab6-4ad1-4ddb-b37f-64c439260fcc</packageId>
      <packageName>Intent.ApplicationTemplate.Aws.Lambda.Functions</packageName>
      <stereotypes />
      <metadata />
      <childElements />
    </childElement>
    <childElement id="941aa707-e70a-493d-9e3a-14c3baad74f0" type="Module" typeId="6a811790-b322-4340-8b68-84dae5ffafa8">
      <name>Intent.Eventing.AzureServiceBus</name>
      <display>Intent.Eventing.AzureServiceBus 1.1.7</display>
      <isAbstract>false</isAbstract>
      <value>1.1.7</value>
      <genericTypes />
      <isMapped>false</isMapped>
      <parentFolderId>1f4cee55-0197-49aa-941a-7d4dba029225</parentFolderId>
      <packageId>5d11bab6-4ad1-4ddb-b37f-64c439260fcc</packageId>
      <packageName>Intent.ApplicationTemplate.Aws.Lambda.Functions</packageName>
      <stereotypes />
      <metadata />
      <childElements />
    </childElement>
    <childElement id="ff53793d-c778-4525-8592-28a13099f89e" type="Module" typeId="6a811790-b322-4340-8b68-84dae5ffafa8">
      <name>Intent.Eventing.Contracts</name>
      <display>Intent.Eventing.Contracts 6.0.0</display>
      <isAbstract>false</isAbstract>
      <value>6.0.0</value>
      <genericTypes />
      <isMapped>false</isMapped>
      <parentFolderId>1f4cee55-0197-49aa-941a-7d4dba029225</parentFolderId>
      <packageId>5d11bab6-4ad1-4ddb-b37f-64c439260fcc</packageId>
      <packageName>Intent.ApplicationTemplate.Aws.Lambda.Functions</packageName>
      <stereotypes />
      <metadata />
      <childElements />
    </childElement>
    <childElement id="3a20661b-bf82-4fc0-af1a-4bda123e988a" type="Module" typeId="6a811790-b322-4340-8b68-84dae5ffafa8">
      <name>Intent.Eventing.Contracts.DomainMapping</name>
      <display>Intent.Eventing.Contracts.DomainMapping 4.2.0</display>
      <isAbstract>false</isAbstract>
      <value>4.2.0</value>
      <genericTypes />
      <isMapped>false</isMapped>
      <parentFolderId>1f4cee55-0197-49aa-941a-7d4dba029225</parentFolderId>
      <packageId>5d11bab6-4ad1-4ddb-b37f-64c439260fcc</packageId>
      <packageName>Intent.ApplicationTemplate.Aws.Lambda.Functions</packageName>
      <stereotypes />
      <metadata />
      <childElements />
    </childElement>
    <childElement id="b8ea1cde-69fe-4f2e-b2f4-d4ddd94aa604" type="Module" typeId="6a811790-b322-4340-8b68-84dae5ffafa8">
      <name>Intent.Eventing.Kafka</name>
      <display>Intent.Eventing.Kafka 1.0.0-beta.33</display>
      <isAbstract>false</isAbstract>
      <value>1.0.0-beta.33</value>
      <genericTypes />
      <isMapped>false</isMapped>
      <parentFolderId>1f4cee55-0197-49aa-941a-7d4dba029225</parentFolderId>
      <packageId>5d11bab6-4ad1-4ddb-b37f-64c439260fcc</packageId>
      <packageName>Intent.ApplicationTemplate.Aws.Lambda.Functions</packageName>
      <stereotypes />
      <metadata />
      <childElements />
    </childElement>
    <childElement id="e984efd7-b0e4-472c-ad99-9bfb83a139bb" type="Module" typeId="6a811790-b322-4340-8b68-84dae5ffafa8">
      <name>Intent.Eventing.MassTransit</name>
      <display>Intent.Eventing.MassTransit 7.0.12</display>
      <isAbstract>false</isAbstract>
      <value>7.0.12</value>
      <genericTypes />
      <isMapped>false</isMapped>
      <parentFolderId>1f4cee55-0197-49aa-941a-7d4dba029225</parentFolderId>
      <packageId>5d11bab6-4ad1-4ddb-b37f-64c439260fcc</packageId>
      <packageName>Intent.ApplicationTemplate.Aws.Lambda.Functions</packageName>
      <stereotypes />
      <metadata />
      <childElements />
    </childElement>
    <childElement id="e92d33aa-7ea2-4701-95e0-3f7ce4cd32d2" type="Module" typeId="6a811790-b322-4340-8b68-84dae5ffafa8">
      <name>Intent.Eventing.MassTransit.EntityFrameworkCore</name>
      <display>Intent.Eventing.MassTransit.EntityFrameworkCore 5.2.5</display>
      <isAbstract>false</isAbstract>
      <value>5.2.5</value>
      <genericTypes />
      <isMapped>false</isMapped>
      <parentFolderId>1f4cee55-0197-49aa-941a-7d4dba029225</parentFolderId>
      <packageId>5d11bab6-4ad1-4ddb-b37f-64c439260fcc</packageId>
      <packageName>Intent.ApplicationTemplate.Aws.Lambda.Functions</packageName>
      <stereotypes />
      <metadata />
      <childElements />
    </childElement>
    <childElement id="1ef8f7d0-4b7d-405c-aeb1-ca41ab675d2a" type="Module" typeId="6a811790-b322-4340-8b68-84dae5ffafa8">
      <name>Intent.Eventing.Solace</name>
      <display>Intent.Eventing.Solace 2.0.14</display>
      <isAbstract>false</isAbstract>
      <value>2.0.14</value>
      <genericTypes />
      <isMapped>false</isMapped>
      <parentFolderId>1f4cee55-0197-49aa-941a-7d4dba029225</parentFolderId>
      <packageId>5d11bab6-4ad1-4ddb-b37f-64c439260fcc</packageId>
      <packageName>Intent.ApplicationTemplate.Aws.Lambda.Functions</packageName>
      <stereotypes />
      <metadata />
      <childElements />
    </childElement>
    <childElement id="992ce245-7b1e-4d89-a4aa-712578fbfc03" type="Module" typeId="6a811790-b322-4340-8b68-84dae5ffafa8">
      <name>Intent.FastEndpoints</name>
      <display>Intent.FastEndpoints 1.0.10</display>
      <isAbstract>false</isAbstract>
      <value>1.0.10</value>
      <genericTypes />
      <isMapped>false</isMapped>
      <parentFolderId>1f4cee55-0197-49aa-941a-7d4dba029225</parentFolderId>
      <packageId>5d11bab6-4ad1-4ddb-b37f-64c439260fcc</packageId>
      <packageName>Intent.ApplicationTemplate.Aws.Lambda.Functions</packageName>
      <stereotypes />
      <metadata />
      <childElements />
    </childElement>
    <childElement id="cebd06fa-be73-4893-a18f-fb1b849ce434" type="Module" typeId="6a811790-b322-4340-8b68-84dae5ffafa8">
      <name>Intent.FastEndpoints.Dispatch.MediatR</name>
      <display>Intent.FastEndpoints.Dispatch.MediatR 1.0.0</display>
      <isAbstract>false</isAbstract>
      <value>1.0.0</value>
      <genericTypes />
      <isMapped>false</isMapped>
      <parentFolderId>1f4cee55-0197-49aa-941a-7d4dba029225</parentFolderId>
      <packageId>5d11bab6-4ad1-4ddb-b37f-64c439260fcc</packageId>
      <packageName>Intent.ApplicationTemplate.Aws.Lambda.Functions</packageName>
      <stereotypes />
      <metadata />
      <childElements />
    </childElement>
    <childElement id="f3fd5225-4d30-431d-88e3-7a38232f6787" type="Module" typeId="6a811790-b322-4340-8b68-84dae5ffafa8">
      <name>Intent.FastEndpoints.Dispatch.Services</name>
      <display>Intent.FastEndpoints.Dispatch.Services 1.0.5</display>
      <isAbstract>false</isAbstract>
      <value>1.0.5</value>
      <genericTypes />
      <isMapped>false</isMapped>
      <parentFolderId>1f4cee55-0197-49aa-941a-7d4dba029225</parentFolderId>
      <packageId>5d11bab6-4ad1-4ddb-b37f-64c439260fcc</packageId>
      <packageName>Intent.ApplicationTemplate.Aws.Lambda.Functions</packageName>
      <stereotypes />
      <metadata />
      <childElements />
    </childElement>
    <childElement id="60df5b18-c644-4f06-9ab2-16b74053caeb" type="Module" typeId="6a811790-b322-4340-8b68-84dae5ffafa8">
      <name>Intent.HotChocolate.GraphQL</name>
      <display>Intent.HotChocolate.GraphQL 5.0.9</display>
      <isAbstract>false</isAbstract>
      <value>5.0.9</value>
      <genericTypes />
      <isMapped>false</isMapped>
      <parentFolderId>1f4cee55-0197-49aa-941a-7d4dba029225</parentFolderId>
      <packageId>5d11bab6-4ad1-4ddb-b37f-64c439260fcc</packageId>
      <packageName>Intent.ApplicationTemplate.Aws.Lambda.Functions</packageName>
      <stereotypes />
      <metadata />
      <childElements />
    </childElement>
    <childElement id="07f4337c-1200-4e4c-9f5d-f554265210b3" type="Module" typeId="6a811790-b322-4340-8b68-84dae5ffafa8">
      <name>Intent.HotChocolate.GraphQL.AspNetCore</name>
      <display>Intent.HotChocolate.GraphQL.AspNetCore 6.0.7</display>
      <isAbstract>false</isAbstract>
      <value>6.0.7</value>
      <genericTypes />
      <isMapped>false</isMapped>
      <parentFolderId>1f4cee55-0197-49aa-941a-7d4dba029225</parentFolderId>
      <packageId>5d11bab6-4ad1-4ddb-b37f-64c439260fcc</packageId>
      <packageName>Intent.ApplicationTemplate.Aws.Lambda.Functions</packageName>
      <stereotypes />
      <metadata />
      <childElements />
    </childElement>
    <childElement id="74dcb9b0-0a00-4578-96ca-3886357b5dcf" type="Module" typeId="6a811790-b322-4340-8b68-84dae5ffafa8">
      <name>Intent.HotChocolate.GraphQL.AzureFunctions</name>
      <display>Intent.HotChocolate.GraphQL.AzureFunctions 2.0.7</display>
      <isAbstract>false</isAbstract>
      <value>2.0.7</value>
      <genericTypes />
      <isMapped>false</isMapped>
      <parentFolderId>1f4cee55-0197-49aa-941a-7d4dba029225</parentFolderId>
      <packageId>5d11bab6-4ad1-4ddb-b37f-64c439260fcc</packageId>
      <packageName>Intent.ApplicationTemplate.Aws.Lambda.Functions</packageName>
      <stereotypes />
      <metadata />
      <childElements />
    </childElement>
    <childElement id="6ec4607c-19de-4eae-afff-d4d40d31c204" type="Module" typeId="6a811790-b322-4340-8b68-84dae5ffafa8">
      <name>Intent.HotChocolate.GraphQL.Dispatch.MediatR</name>
      <display>Intent.HotChocolate.GraphQL.Dispatch.MediatR 2.0.1</display>
      <isAbstract>false</isAbstract>
      <value>2.0.1</value>
      <genericTypes />
      <isMapped>false</isMapped>
      <parentFolderId>1f4cee55-0197-49aa-941a-7d4dba029225</parentFolderId>
      <packageId>5d11bab6-4ad1-4ddb-b37f-64c439260fcc</packageId>
      <packageName>Intent.ApplicationTemplate.Aws.Lambda.Functions</packageName>
      <stereotypes />
      <metadata />
      <childElements />
    </childElement>
    <childElement id="d43a7b0e-5173-4d8b-bbb9-fd1e923afe4f" type="Module" typeId="6a811790-b322-4340-8b68-84dae5ffafa8">
      <name>Intent.HotChocolate.GraphQL.Dispatch.Services</name>
      <display>Intent.HotChocolate.GraphQL.Dispatch.Services 2.0.1</display>
      <isAbstract>false</isAbstract>
      <value>2.0.1</value>
      <genericTypes />
      <isMapped>false</isMapped>
      <parentFolderId>1f4cee55-0197-49aa-941a-7d4dba029225</parentFolderId>
      <packageId>5d11bab6-4ad1-4ddb-b37f-64c439260fcc</packageId>
      <packageName>Intent.ApplicationTemplate.Aws.Lambda.Functions</packageName>
      <stereotypes />
      <metadata />
      <childElements />
    </childElement>
    <childElement id="c60809af-9c71-4707-891a-d5b165bae8ce" type="Module" typeId="6a811790-b322-4340-8b68-84dae5ffafa8">
      <name>Intent.MediatR.DomainEvents</name>
      <display>Intent.MediatR.DomainEvents 5.2.4</display>
      <isAbstract>false</isAbstract>
      <value>5.2.4</value>
      <genericTypes />
      <isMapped>false</isMapped>
      <parentFolderId>1f4cee55-0197-49aa-941a-7d4dba029225</parentFolderId>
      <packageId>5d11bab6-4ad1-4ddb-b37f-64c439260fcc</packageId>
      <packageName>Intent.ApplicationTemplate.Aws.Lambda.Functions</packageName>
      <stereotypes />
      <metadata />
      <childElements />
    </childElement>
    <childElement id="a14d8969-0c05-48b0-929e-eddcc3e38d5b" type="Module" typeId="6a811790-b322-4340-8b68-84dae5ffafa8">
      <name>Intent.Metadata.DocumentDB</name>
      <display>Intent.Metadata.DocumentDB 1.3.6</display>
      <isAbstract>false</isAbstract>
      <value>1.3.6</value>
      <genericTypes />
      <isMapped>false</isMapped>
      <parentFolderId>1f4cee55-0197-49aa-941a-7d4dba029225</parentFolderId>
      <packageId>5d11bab6-4ad1-4ddb-b37f-64c439260fcc</packageId>
      <packageName>Intent.ApplicationTemplate.Aws.Lambda.Functions</packageName>
      <stereotypes />
      <metadata />
      <childElements />
    </childElement>
    <childElement id="d77c20b0-f31d-468e-b412-a76ff60e5d85" type="Module" typeId="6a811790-b322-4340-8b68-84dae5ffafa8">
      <name>Intent.Metadata.RDBMS</name>
      <display>Intent.Metadata.RDBMS 3.7.9</display>
      <isAbstract>false</isAbstract>
      <value>3.7.9</value>
      <genericTypes />
      <isMapped>false</isMapped>
      <parentFolderId>1f4cee55-0197-49aa-941a-7d4dba029225</parentFolderId>
      <packageId>5d11bab6-4ad1-4ddb-b37f-64c439260fcc</packageId>
      <packageName>Intent.ApplicationTemplate.Aws.Lambda.Functions</packageName>
      <stereotypes />
      <metadata />
      <childElements />
    </childElement>
    <childElement id="6e75de13-9a1f-43cb-a0c0-230060b0425c" type="Module" typeId="6a811790-b322-4340-8b68-84dae5ffafa8">
      <name>Intent.Metadata.Security</name>
      <display>Intent.Metadata.Security 1.1.2</display>
      <isAbstract>false</isAbstract>
      <value>1.1.2</value>
      <genericTypes />
      <isMapped>false</isMapped>
      <parentFolderId>1f4cee55-0197-49aa-941a-7d4dba029225</parentFolderId>
      <packageId>5d11bab6-4ad1-4ddb-b37f-64c439260fcc</packageId>
      <packageName>Intent.ApplicationTemplate.Aws.Lambda.Functions</packageName>
      <stereotypes />
      <metadata />
      <childElements />
    </childElement>
    <childElement id="3bb16ba8-7dbb-4ab0-b711-f1aecee76c59" type="Module" typeId="6a811790-b322-4340-8b68-84dae5ffafa8">
      <name>Intent.Metadata.WebApi</name>
      <display>Intent.Metadata.WebApi 4.7.17</display>
      <isAbstract>false</isAbstract>
      <value>4.7.17</value>
      <genericTypes />
      <isMapped>false</isMapped>
      <parentFolderId>1f4cee55-0197-49aa-941a-7d4dba029225</parentFolderId>
      <packageId>5d11bab6-4ad1-4ddb-b37f-64c439260fcc</packageId>
      <packageName>Intent.ApplicationTemplate.Aws.Lambda.Functions</packageName>
      <stereotypes />
      <metadata />
      <childElements />
    </childElement>
    <childElement id="1997d47e-5852-424a-b3eb-a7004b7dd434" type="Module" typeId="6a811790-b322-4340-8b68-84dae5ffafa8">
      <name>Intent.Modelers.Domain</name>
      <display>Intent.Modelers.Domain 3.12.10</display>
      <isAbstract>false</isAbstract>
      <value>3.12.10</value>
      <genericTypes />
      <isMapped>false</isMapped>
      <parentFolderId>1f4cee55-0197-49aa-941a-7d4dba029225</parentFolderId>
      <packageId>5d11bab6-4ad1-4ddb-b37f-64c439260fcc</packageId>
      <packageName>Intent.ApplicationTemplate.Aws.Lambda.Functions</packageName>
      <stereotypes />
      <metadata />
      <childElements />
    </childElement>
    <childElement id="f863df02-7222-417a-ba57-8653e8a23840" type="Module" typeId="6a811790-b322-4340-8b68-84dae5ffafa8">
      <name>Intent.Modelers.Domain.Events</name>
      <display>Intent.Modelers.Domain.Events 4.4.5</display>
      <isAbstract>false</isAbstract>
      <value>4.4.5</value>
      <genericTypes />
      <isMapped>false</isMapped>
      <parentFolderId>1f4cee55-0197-49aa-941a-7d4dba029225</parentFolderId>
      <packageId>5d11bab6-4ad1-4ddb-b37f-64c439260fcc</packageId>
      <packageName>Intent.ApplicationTemplate.Aws.Lambda.Functions</packageName>
      <stereotypes />
      <metadata />
      <childElements />
    </childElement>
    <childElement id="ac9252c2-ac51-41fd-8419-1bf8f659b012" type="Module" typeId="6a811790-b322-4340-8b68-84dae5ffafa8">
      <name>Intent.Modelers.Domain.Repositories</name>
      <display>Intent.Modelers.Domain.Repositories 3.6.1</display>
      <isAbstract>false</isAbstract>
      <value>3.6.1</value>
      <genericTypes />
      <isMapped>false</isMapped>
      <parentFolderId>1f4cee55-0197-49aa-941a-7d4dba029225</parentFolderId>
      <packageId>5d11bab6-4ad1-4ddb-b37f-64c439260fcc</packageId>
      <packageName>Intent.ApplicationTemplate.Aws.Lambda.Functions</packageName>
      <stereotypes />
      <metadata />
      <childElements />
    </childElement>
    <childElement id="1c944231-8eb7-404f-bf3b-ca6a5abff6e6" type="Module" typeId="6a811790-b322-4340-8b68-84dae5ffafa8">
      <name>Intent.Modelers.Domain.Services</name>
      <display>Intent.Modelers.Domain.Services 1.3.0</display>
      <isAbstract>false</isAbstract>
      <value>1.3.0</value>
      <genericTypes />
      <isMapped>false</isMapped>
      <parentFolderId>1f4cee55-0197-49aa-941a-7d4dba029225</parentFolderId>
      <packageId>5d11bab6-4ad1-4ddb-b37f-64c439260fcc</packageId>
      <packageName>Intent.ApplicationTemplate.Aws.Lambda.Functions</packageName>
      <stereotypes />
      <metadata />
      <childElements />
    </childElement>
    <childElement id="22a2ae02-5ceb-4024-ac3e-1cf3eb10b776" type="Module" typeId="6a811790-b322-4340-8b68-84dae5ffafa8">
      <name>Intent.Modelers.Domain.ValueObjects</name>
      <display>Intent.Modelers.Domain.ValueObjects 3.6.2</display>
      <isAbstract>false</isAbstract>
      <value>3.6.2</value>
      <genericTypes />
      <isMapped>false</isMapped>
      <parentFolderId>1f4cee55-0197-49aa-941a-7d4dba029225</parentFolderId>
      <packageId>5d11bab6-4ad1-4ddb-b37f-64c439260fcc</packageId>
      <packageName>Intent.ApplicationTemplate.Aws.Lambda.Functions</packageName>
      <stereotypes />
      <metadata />
      <childElements />
    </childElement>
    <childElement id="19b468f9-26af-411c-a6da-c76af7e4d33d" type="Module" typeId="6a811790-b322-4340-8b68-84dae5ffafa8">
      <name>Intent.Modelers.Eventing</name>
      <display>Intent.Modelers.Eventing 6.0.3</display>
      <isAbstract>false</isAbstract>
      <value>6.0.3</value>
      <genericTypes />
      <isMapped>false</isMapped>
      <parentFolderId>1f4cee55-0197-49aa-941a-7d4dba029225</parentFolderId>
      <packageId>5d11bab6-4ad1-4ddb-b37f-64c439260fcc</packageId>
      <packageName>Intent.ApplicationTemplate.Aws.Lambda.Functions</packageName>
      <stereotypes />
      <metadata />
      <childElements />
    </childElement>
    <childElement id="6edf3479-ea25-4a1b-9f5b-65408c6b3c7c" type="Module" typeId="6a811790-b322-4340-8b68-84dae5ffafa8">
      <name>Intent.Modelers.ServiceProxies</name>
      <display>Intent.Modelers.ServiceProxies 5.2.3</display>
      <isAbstract>false</isAbstract>
      <value>5.2.3</value>
      <genericTypes />
      <isMapped>false</isMapped>
      <parentFolderId>1f4cee55-0197-49aa-941a-7d4dba029225</parentFolderId>
      <packageId>5d11bab6-4ad1-4ddb-b37f-64c439260fcc</packageId>
      <packageName>Intent.ApplicationTemplate.Aws.Lambda.Functions</packageName>
      <stereotypes />
      <metadata />
      <childElements />
    </childElement>
    <childElement id="8e2820d6-785a-4b7b-85f8-4202a02d1715" type="Module" typeId="6a811790-b322-4340-8b68-84dae5ffafa8">
      <name>Intent.Modelers.Services</name>
      <display>Intent.Modelers.Services 4.0.8</display>
      <isAbstract>false</isAbstract>
      <value>4.0.8</value>
      <genericTypes />
      <isMapped>false</isMapped>
      <parentFolderId>1f4cee55-0197-49aa-941a-7d4dba029225</parentFolderId>
      <packageId>5d11bab6-4ad1-4ddb-b37f-64c439260fcc</packageId>
      <packageName>Intent.ApplicationTemplate.Aws.Lambda.Functions</packageName>
      <stereotypes />
      <metadata />
      <childElements />
    </childElement>
    <childElement id="f30a8f71-b418-44de-8d97-4bd9de2e182f" type="Module" typeId="6a811790-b322-4340-8b68-84dae5ffafa8">
      <name>Intent.Modelers.Services.CQRS</name>
      <display>Intent.Modelers.Services.CQRS 6.0.4</display>
      <isAbstract>false</isAbstract>
      <value>6.0.4</value>
      <genericTypes />
      <isMapped>false</isMapped>
      <parentFolderId>1f4cee55-0197-49aa-941a-7d4dba029225</parentFolderId>
      <packageId>5d11bab6-4ad1-4ddb-b37f-64c439260fcc</packageId>
      <packageName>Intent.ApplicationTemplate.Aws.Lambda.Functions</packageName>
      <stereotypes />
      <metadata />
      <childElements />
    </childElement>
    <childElement id="58932b96-4bd9-41f0-a68c-4c36a9da6603" type="Module" typeId="6a811790-b322-4340-8b68-84dae5ffafa8">
      <name>Intent.Modelers.Services.DomainInteractions</name>
      <display>Intent.Modelers.Services.DomainInteractions 2.3.10</display>
      <isAbstract>false</isAbstract>
      <value>2.3.10</value>
      <genericTypes />
      <isMapped>false</isMapped>
      <parentFolderId>1f4cee55-0197-49aa-941a-7d4dba029225</parentFolderId>
      <packageId>5d11bab6-4ad1-4ddb-b37f-64c439260fcc</packageId>
      <packageName>Intent.ApplicationTemplate.Aws.Lambda.Functions</packageName>
      <stereotypes />
      <metadata />
      <childElements />
    </childElement>
    <childElement id="b1e3f755-f3dc-4238-8295-6a4474f53cf7" type="Module" typeId="6a811790-b322-4340-8b68-84dae5ffafa8">
      <name>Intent.Modelers.Services.EventInteractions</name>
      <display>Intent.Modelers.Services.EventInteractions 2.0.4</display>
      <isAbstract>false</isAbstract>
      <value>2.0.4</value>
      <genericTypes />
      <isMapped>false</isMapped>
      <parentFolderId>1f4cee55-0197-49aa-941a-7d4dba029225</parentFolderId>
      <packageId>5d11bab6-4ad1-4ddb-b37f-64c439260fcc</packageId>
      <packageName>Intent.ApplicationTemplate.Aws.Lambda.Functions</packageName>
      <stereotypes />
      <metadata />
      <childElements />
    </childElement>
    <childElement id="2f1df9c4-9b7c-4ede-b40f-491274b0c85f" type="Module" typeId="6a811790-b322-4340-8b68-84dae5ffafa8">
      <name>Intent.Modelers.Services.GraphQL</name>
      <display>Intent.Modelers.Services.GraphQL 1.1.0</display>
      <isAbstract>false</isAbstract>
      <value>1.1.0</value>
      <genericTypes />
      <isMapped>false</isMapped>
      <parentFolderId>1f4cee55-0197-49aa-941a-7d4dba029225</parentFolderId>
      <packageId>5d11bab6-4ad1-4ddb-b37f-64c439260fcc</packageId>
      <packageName>Intent.ApplicationTemplate.Aws.Lambda.Functions</packageName>
      <stereotypes />
      <metadata />
      <childElements />
    </childElement>
    <childElement id="0b9572ce-3741-410e-a1e8-593eb88170a5" type="Module" typeId="6a811790-b322-4340-8b68-84dae5ffafa8">
      <name>Intent.Modelers.Types.ServiceProxies</name>
      <display>Intent.Modelers.Types.ServiceProxies 5.5.3</display>
      <isAbstract>false</isAbstract>
      <value>5.5.3</value>
      <genericTypes />
      <isMapped>false</isMapped>
      <parentFolderId>1f4cee55-0197-49aa-941a-7d4dba029225</parentFolderId>
      <packageId>5d11bab6-4ad1-4ddb-b37f-64c439260fcc</packageId>
      <packageName>Intent.ApplicationTemplate.Aws.Lambda.Functions</packageName>
      <stereotypes />
      <metadata />
      <childElements />
    </childElement>
    <childElement id="f581c88c-f262-4309-8aa1-30d70c969d83" type="Module" typeId="6a811790-b322-4340-8b68-84dae5ffafa8">
      <name>Intent.Modelers.UI</name>
      <display>Intent.Modelers.UI 1.0.4</display>
      <isAbstract>false</isAbstract>
      <value>1.0.4</value>
      <genericTypes />
      <isMapped>false</isMapped>
      <parentFolderId>1f4cee55-0197-49aa-941a-7d4dba029225</parentFolderId>
      <packageId>5d11bab6-4ad1-4ddb-b37f-64c439260fcc</packageId>
      <packageName>Intent.ApplicationTemplate.Aws.Lambda.Functions</packageName>
      <stereotypes />
      <metadata />
      <childElements />
    </childElement>
    <childElement id="5d6d3241-a630-4044-af5f-4bf8f8d4e968" type="Module" typeId="6a811790-b322-4340-8b68-84dae5ffafa8">
      <name>Intent.Modelers.UI.Core</name>
      <display>Intent.Modelers.UI.Core 1.0.0</display>
      <isAbstract>false</isAbstract>
      <value>1.0.0</value>
      <genericTypes />
      <isMapped>false</isMapped>
      <parentFolderId>1f4cee55-0197-49aa-941a-7d4dba029225</parentFolderId>
      <packageId>5d11bab6-4ad1-4ddb-b37f-64c439260fcc</packageId>
      <packageName>Intent.ApplicationTemplate.Aws.Lambda.Functions</packageName>
      <stereotypes />
      <metadata />
      <childElements />
    </childElement>
    <childElement id="ff0f6620-a37a-40cb-9aed-344159c9d1fd" type="Module" typeId="6a811790-b322-4340-8b68-84dae5ffafa8">
      <name>Intent.Modelers.UI.ServiceProxies</name>
      <display>Intent.Modelers.UI.ServiceProxies 1.0.0</display>
      <isAbstract>false</isAbstract>
      <value>1.0.0</value>
      <genericTypes />
      <isMapped>false</isMapped>
      <parentFolderId>1f4cee55-0197-49aa-941a-7d4dba029225</parentFolderId>
      <packageId>5d11bab6-4ad1-4ddb-b37f-64c439260fcc</packageId>
      <packageName>Intent.ApplicationTemplate.Aws.Lambda.Functions</packageName>
      <stereotypes />
      <metadata />
      <childElements />
    </childElement>
    <childElement id="523b2d37-1572-4d56-8827-a4eb0ef50f49" type="Module" typeId="6a811790-b322-4340-8b68-84dae5ffafa8">
      <name>Intent.Modules.AspNetCore.Logging.Serilog</name>
      <display>Intent.Modules.AspNetCore.Logging.Serilog 5.3.4</display>
      <isAbstract>false</isAbstract>
      <value>5.3.4</value>
      <genericTypes />
      <isMapped>false</isMapped>
      <parentFolderId>1f4cee55-0197-49aa-941a-7d4dba029225</parentFolderId>
      <packageId>5d11bab6-4ad1-4ddb-b37f-64c439260fcc</packageId>
      <packageName>Intent.ApplicationTemplate.Aws.Lambda.Functions</packageName>
      <stereotypes />
      <metadata />
      <childElements />
    </childElement>
    <childElement id="d031d1d0-b90b-47fb-97dc-f8c467cb7121" type="Module" typeId="6a811790-b322-4340-8b68-84dae5ffafa8">
      <name>Intent.Modules.AspNetCore.MultiTenancy</name>
      <display>Intent.Modules.AspNetCore.MultiTenancy 5.1.19</display>
      <isAbstract>false</isAbstract>
      <value>5.1.19</value>
      <genericTypes />
      <isMapped>false</isMapped>
      <parentFolderId>1f4cee55-0197-49aa-941a-7d4dba029225</parentFolderId>
      <packageId>5d11bab6-4ad1-4ddb-b37f-64c439260fcc</packageId>
      <packageName>Intent.ApplicationTemplate.Aws.Lambda.Functions</packageName>
      <stereotypes />
      <metadata />
      <childElements />
    </childElement>
    <childElement id="78b9611d-b87d-4835-87a3-15ff30354ce4" type="Module" typeId="6a811790-b322-4340-8b68-84dae5ffafa8">
      <name>Intent.Modules.Modelers.Domain.StoredProcedures</name>
      <display>Intent.Modules.Modelers.Domain.StoredProcedures 1.2.2</display>
      <isAbstract>false</isAbstract>
      <value>1.2.2</value>
      <genericTypes />
      <isMapped>false</isMapped>
      <parentFolderId>1f4cee55-0197-49aa-941a-7d4dba029225</parentFolderId>
      <packageId>5d11bab6-4ad1-4ddb-b37f-64c439260fcc</packageId>
      <packageName>Intent.ApplicationTemplate.Aws.Lambda.Functions</packageName>
      <stereotypes />
      <metadata />
      <childElements />
    </childElement>
    <childElement id="1f2fd8e3-e49a-47d6-badf-fc50a5ce7a70" type="Module" typeId="6a811790-b322-4340-8b68-84dae5ffafa8">
      <name>Intent.MongoDb</name>
      <display>Intent.MongoDb 2.0.7</display>
      <isAbstract>false</isAbstract>
      <value>2.0.7</value>
      <genericTypes />
      <isMapped>false</isMapped>
      <parentFolderId>1f4cee55-0197-49aa-941a-7d4dba029225</parentFolderId>
      <packageId>5d11bab6-4ad1-4ddb-b37f-64c439260fcc</packageId>
      <packageName>Intent.ApplicationTemplate.Aws.Lambda.Functions</packageName>
      <stereotypes />
      <metadata />
      <childElements />
    </childElement>
    <childElement id="abf3ecd5-6ae7-4b7d-95e5-a24ce7adfeff" type="Module" typeId="6a811790-b322-4340-8b68-84dae5ffafa8">
      <name>Intent.OpenTelemetry</name>
      <display>Intent.OpenTelemetry 2.2.14</display>
      <isAbstract>false</isAbstract>
      <value>2.2.14</value>
      <genericTypes />
      <isMapped>false</isMapped>
      <parentFolderId>1f4cee55-0197-49aa-941a-7d4dba029225</parentFolderId>
      <packageId>5d11bab6-4ad1-4ddb-b37f-64c439260fcc</packageId>
      <packageName>Intent.ApplicationTemplate.Aws.Lambda.Functions</packageName>
      <stereotypes />
      <metadata />
      <childElements />
    </childElement>
    <childElement id="d83efce8-e721-4d35-8a37-96883efe7e6f" type="Module" typeId="6a811790-b322-4340-8b68-84dae5ffafa8">
      <name>Intent.OutputManager.RoslynWeaver</name>
      <display>Intent.OutputManager.RoslynWeaver 4.9.16</display>
      <isAbstract>false</isAbstract>
      <value>4.9.16</value>
      <genericTypes />
      <isMapped>false</isMapped>
      <parentFolderId>1f4cee55-0197-49aa-941a-7d4dba029225</parentFolderId>
      <packageId>5d11bab6-4ad1-4ddb-b37f-64c439260fcc</packageId>
      <packageName>Intent.ApplicationTemplate.Aws.Lambda.Functions</packageName>
      <stereotypes />
      <metadata />
      <childElements />
    </childElement>
    <childElement id="0cca2a96-c59b-4ffe-a7af-a87c4503a941" type="Module" typeId="6a811790-b322-4340-8b68-84dae5ffafa8">
      <name>Intent.Redis.Om.Repositories</name>
      <display>Intent.Redis.Om.Repositories 1.0.18</display>
      <isAbstract>false</isAbstract>
      <value>1.0.18</value>
      <genericTypes />
      <isMapped>false</isMapped>
      <parentFolderId>1f4cee55-0197-49aa-941a-7d4dba029225</parentFolderId>
      <packageId>5d11bab6-4ad1-4ddb-b37f-64c439260fcc</packageId>
      <packageName>Intent.ApplicationTemplate.Aws.Lambda.Functions</packageName>
      <stereotypes />
      <metadata />
      <childElements />
    </childElement>
    <childElement id="ea8b3806-451b-4a88-b7d9-1d7725ef96cd" type="Module" typeId="6a811790-b322-4340-8b68-84dae5ffafa8">
      <name>Intent.Security.JWT</name>
      <display>Intent.Security.JWT 4.3.6</display>
      <isAbstract>false</isAbstract>
      <value>4.3.6</value>
      <genericTypes />
      <isMapped>false</isMapped>
      <parentFolderId>1f4cee55-0197-49aa-941a-7d4dba029225</parentFolderId>
      <packageId>5d11bab6-4ad1-4ddb-b37f-64c439260fcc</packageId>
      <packageName>Intent.ApplicationTemplate.Aws.Lambda.Functions</packageName>
      <stereotypes />
      <metadata />
      <childElements />
    </childElement>
    <childElement id="935b9f94-dee7-4775-8c54-610186156ea0" type="Module" typeId="6a811790-b322-4340-8b68-84dae5ffafa8">
      <name>Intent.Security.MSAL</name>
      <display>Intent.Security.MSAL 4.3.6</display>
      <isAbstract>false</isAbstract>
      <value>4.3.6</value>
      <genericTypes />
      <isMapped>false</isMapped>
      <parentFolderId>1f4cee55-0197-49aa-941a-7d4dba029225</parentFolderId>
      <packageId>5d11bab6-4ad1-4ddb-b37f-64c439260fcc</packageId>
      <packageName>Intent.ApplicationTemplate.Aws.Lambda.Functions</packageName>
      <stereotypes />
      <metadata />
      <childElements />
    </childElement>
    <childElement id="d8b850a6-31e3-429a-8450-e8b72bb06fa8" type="Module" typeId="6a811790-b322-4340-8b68-84dae5ffafa8">
      <name>Intent.UnitTesting</name>
      <display>Intent.UnitTesting 1.0.3</display>
      <isAbstract>false</isAbstract>
      <value>1.0.3</value>
      <genericTypes />
      <isMapped>false</isMapped>
      <parentFolderId>1f4cee55-0197-49aa-941a-7d4dba029225</parentFolderId>
      <packageId>5d11bab6-4ad1-4ddb-b37f-64c439260fcc</packageId>
      <packageName>Intent.ApplicationTemplate.Aws.Lambda.Functions</packageName>
      <stereotypes />
      <metadata />
      <childElements />
    </childElement>
    <childElement id="08aa96d8-6a50-492b-af01-0b7e8eb67fae" type="Module" typeId="6a811790-b322-4340-8b68-84dae5ffafa8">
      <name>Intent.VisualStudio.Projects</name>
      <display>Intent.VisualStudio.Projects 3.9.8</display>
      <isAbstract>false</isAbstract>
      <value>3.9.8</value>
      <genericTypes />
      <isMapped>false</isMapped>
      <parentFolderId>1f4cee55-0197-49aa-941a-7d4dba029225</parentFolderId>
      <packageId>5d11bab6-4ad1-4ddb-b37f-64c439260fcc</packageId>
      <packageName>Intent.ApplicationTemplate.Aws.Lambda.Functions</packageName>
      <stereotypes />
      <metadata />
      <childElements />
    </childElement>
    <childElement id="d18c9fd5-9166-49ef-9bd7-b22a70dcf894" type="Module" typeId="6a811790-b322-4340-8b68-84dae5ffafa8">
      <name>Intent.WindowsServiceHost</name>
      <display>Intent.WindowsServiceHost 1.0.15</display>
      <isAbstract>false</isAbstract>
      <value>1.0.15</value>
      <genericTypes />
      <isMapped>false</isMapped>
      <parentFolderId>1f4cee55-0197-49aa-941a-7d4dba029225</parentFolderId>
      <packageId>5d11bab6-4ad1-4ddb-b37f-64c439260fcc</packageId>
      <packageName>Intent.ApplicationTemplate.Aws.Lambda.Functions</packageName>
      <stereotypes />
      <metadata />
      <childElements />
    </childElement>
  </childElements>
</class>